mkdocs_issue_showcaser/__init__.py
mkdocs_issue_showcaser/plugin.py
mkdocs_issue_showcaser-0.1.1.dist-info/METADATA
mkdocs_issue_showcaser-0.1.1.dist-info/WHEEL
mkdocs_issue_showcaser-0.1.1.dist-info/entry_points.txt
mkdocs_issue_showcaser-0.1.1.dist-info/top_level.txt
mkdocs_issue_showcaser-0.1.1.dist-info/RECORD
